hatch_external_dependencies/hooks.py
hatch_external_dependencies-1.0.7.dist-info/METADATA
hatch_external_dependencies-1.0.7.dist-info/WHEEL
hatch_external_dependencies-1.0.7.dist-info/entry_points.txt
hatch_external_dependencies-1.0.7.dist-info/RECORD
