Metadata-Version: 2.3
Name: hatch-external-dependencies
Version: 1.0.7
Summary: Hatch plugin for adding `Requires-External` metadata in built packages
Author-email: Jimmy Huguet <jimmy.huguet@skillcorner.com>
Classifier: Framework :: Hatch
Requires-Python: >=3.9
Requires-Dist: hatchling
